sullivan/__init__.py
sullivan/cli.py
tests/__init__.py
tests/test_cli.py
sullivan-0.1.2.dist-info/LICENSE
sullivan-0.1.2.dist-info/METADATA
sullivan-0.1.2.dist-info/WHEEL
sullivan-0.1.2.dist-info/entry_points.txt
sullivan-0.1.2.dist-info/top_level.txt
sullivan-0.1.2.dist-info/RECORD
