Metadata-Version: 2.1
Name: sullivan
Version: 0.1.2
Summary: Cargo for Python - a hassle-free package manager for Python
Home-page: https://github.com/viraatdas/sullivan
Author: Viraat Das
Author-email: viraat.laldas@gmail.com
Classifier: Programming Language :: Python :: 3
Classifier: License :: OSI Approved :: MIT License
Classifier: Operating System :: OS Independent
Requires-Python: >=3.6
License-File: LICENSE
Requires-Dist: click
Requires-Dist: toml
